myadipkgsagar
