Metadata-Version: 2.1
Name: sagarpkgtest
Version: 0.0.2
Summary: ADI python Package module
Home-page: https://github.com/Sagya7/python_day2_capstone.git
Author: sagar
Author-email: sagarwalishettiiitm@gmail.com
License: UNKNOWN
Platform: UNKNOWN
Classifier: Programming Language :: Python :: 3
Classifier: Operating System :: OS Independent
